{
  "locations": {
    "0": {
      "objects": [
        "GG",
        "GG",
        "GG",
        "GG",
        "GG",
        "GG",
        "GG",
        "GG",
        "GG",
        "GG",
        "GG",
        "GG",
        "GG",
        "GG",
        "GG",
        "GG",
        "GG   B",
        "GG",
        "GG",
        "GG",
        "GG   W",
        "GG   B",
        "GG   W   B",
        "GG   B",
        "GG   W",
        "GG",
        "GG",
        "GG",
        "GG<{",
        "GG>}",
        "GG",
        "GG",
        "GG",
        "GG",
        "GG",
        "GG",
        "GG",
        "GG",
        "GG<<{",
        "GG>>}",
        "GG",
        "GG",
        "GG",
        "GG",
        "GG",
        "GG",
        "GG<<<{",
        "GG>>>}",
        "GG",
        "GG",
        "GG",
        "GG",
        "GG",
        "GG",
        "GG",
        "GG",
        "GG",
        "GG<<<{",
        "GG>>>}",
        "GG",
        "GG",
        "GG",
        "GG",
        "GG",
        "GG    B",
        "GG",
        "GG",
        "GG",
        "GG",
        "",
        "",
        "GG",
        "GG",
        "GG",
        "GG",
        "GG",
        "GG",
        "GG   W",
        "GG   B",
        "GG   W",
        "GG       W",
        "GG       W",
        "GG       W",
        "GG       W",
        "GG       W",
        "GG       W",
        "         W",
        "         W",
        "",
        "GG",
        "GG",
        "GG       W",
        "GG       W",
        "GG       W",
        "GG   B   B",
        "GG",
        "GG",
        "GG",
        "GG",
        "GG",
        "GG   W",
        "GG   B",
        "GG",
        "GG",
        "GG",
        "GG",
        "GG   B",
        "GG",
        "GG",
        "GG   B   B",
        "GG",
        "GG",
        "GG   B",
        "GG",
        "GG",
        "GG",
        "GG",
        "GG",
        "GG   W",
        "GG",
        "GG",
        "GG       W",
        "GG       W",
        "GG       W",
        "GG",
        "GG",
        "GG",
        "GG",
        "GG       W",
        "GG   W   B",
        "GG   W   B",
        "GG       w",
        "GG",
        "GG",
        "GGS",
        "GGSS",
        "GGSSS",
        "GGSSSS",
        "GG",
        "GG",
        "GGSSSS",
        "GGSSS",
        "GGSS",
        "GGS",
        "GG",
        "GG",
        "GG",
        "GG",
        "GGS",
        "GGSS",
        "GGSSS",
        "GGSSSS",
        "GGSSSS",
        "",
        "",
        "GGSSSS",
        "GGSSS",
        "GGSS",
        "GGS",
        "GG",
        "GG",
        "GG",
        "GG",
        "GG<{",
        "GG>}",
        "GG",
        "GG",
        "GG",
        "GG   W",
        "GG   W",
        "GG   B",
        "GG   W",
        "GG",
        "GG",
        "GG",
        "GG",
        "GG",
        "GG",
        "GG",
        "GG<{",
        "GG>}",
        "GGS",
        "GGSS",
        "GGSSS",
        "GGSSSS",
        "GGSSSSS",
        "GGSSSSSS",
        "GGSSSSSSS",
        "GGSSSSSSSS",
        "GGSSSSSSSS",
        "GG",
        "GG",
        "GG",
        "GG",
        "GG",
        "GG",
        "GG",
        "GG",
        "GGSFFFFFFFFFf",
        "GG",
        "GG",
        "GG",
        "GGww4",
        "GGww354",
        "GG123w7",
        "GGww364",
        "GGww4",
        "GG",
        "GG",
        "GG",
        "GG",
        "GG",
        "GG",
        "GG",
        "GG",
        "GG",
        "GG",
        "GG",
        "GG",
        "GG",
        "GG",
        "GG",
        "GG",
        "GG"
      ],
      "backgrounds": {
        "cloud": [
          [8, 11],
          [19, 12],
          [27, 11],
          [28, 11],
          [29, 11],
          [36, 12],
          [37, 12],
          [56, 11],
          [67, 12],
          [75, 11],
          [76, 11],
          [77, 11],
          [84, 12],
          [85, 12],
          [104, 11],
          [115, 12],
          [123, 11],
          [124, 11],
          [125, 11],
          [132, 12],
          [133, 12],
          [152, 11],
          [163, 12],
          [171, 11],
          [172, 11],
          [173, 11],
          [180, 12],
          [181, 12],
          [200, 11],
          [211, 12],
          [219, 11],
          [220, 11],
          [221, 11]
        ],
        "hillLeft": [
          [0, 2],
          [1, 3],
          [16, 2],
          [48, 2],
          [49, 3],
          [64, 2],
          [96, 2],
          [97, 3],
          [112, 2],
          [144, 2],
          [145, 3],
          [160, 2],
          [192, 2],
          [193, 3],
          [208, 2]
        ],
        "hillTop": [
          [2, 4],
          [17, 3],
          [50, 4],
          [65, 3],
          [98, 4],
          [113, 3],
          [146, 4],
          [161, 3],
          [194, 4],
          [209, 3]
        ],
        "hillRight": [
          [4, 2],
          [3, 3],
          [18, 2],
          [51, 3],
          [52, 2],
          [66, 2],
          [99, 3],
          [100, 2],
          [114, 2],
          [147, 3],
          [148, 2],
          [162, 2],
          [195, 3],
          [196, 2],
          [210, 2]
        ],
        "hillMiddleLeft":[
          [1, 2],
          [2, 3],
          [3, 2],
          [17, 2],
          [49, 2],
          [50, 3],
          [51, 2],
          [65, 2],
          [97, 2],
          [98, 3],
          [99, 2],
          [113, 2],
          [145, 2],
          [146, 3],
          [147, 2],
          [161, 2],
          [193, 2],
          [194, 3],
          [195, 2],
          [209, 2]
        ],
        "hillMiddle":[
          [2, 2],
          [50, 2],
          [98, 2],
          [146, 2],
          [194, 2]
        ],
        "bush": [
          [11, 2],
          [12, 2],
          [13, 2],
          [23, 2],
          [41, 2],
          [42, 2],
          [59, 2],
          [60, 2],
          [61, 2],
          [71, 2],
          [89, 2],
          [90, 2],
          [107, 2],
          [108, 2],
          [109, 2],
          [119, 2],
          [137, 2],
          [138, 2],
          [157, 2],
          [167, 2],
          [206, 2],
          [215, 2]
        ]
      }
    }
  }
}

